{"v":"4.8.0","meta":{"g":"LottieFiles AE 3.4.5","a":"","k":"","d":"","tc":""},"fr":29.9700012207031,"ip":0,"op":20.0000008146167,"w":350,"h":350,"nm":"팡파레","ddd":0,"assets":[],"layers":[{"ddd":0,"ind":1,"ty":4,"nm":"팡파레","sr":1,"ks":{"o":{"a":0,"k":100,"ix":11},"r":{"a":0,"k":0,"ix":10},"p":{"a":0,"k":[172.5,145,0],"ix":2},"a":{"a":0,"k":[175,175,0],"ix":1},"s":{"a":0,"k":[100,100,100],"ix":6}},"ao":0,"shapes":[{"ty":"gr","it":[{"ind":0,"ty":"sh","ix":1,"ks":{"a":0,"k":{"i":[[-2.209,0],[0,-2.209],[2.209,0],[0,2.209]],"o":[[2.209,0],[0,2.209],[-2.209,0],[0,-2.209]],"v":[[0,-4],[4,0],[0,4],[-4,0]],"c":true},"ix":2},"nm":"Path 1","mn":"ADBE Vector Shape - Group","hd":false},{"ty":"fl","c":{"a":0,"k":[1,0.796078491211,0.796078491211,1],"ix":4},"o":{"a":0,"k":100,"ix":5},"r":1,"bm":0,"nm":"Fill 1","mn":"ADBE Vector Graphic - Fill","hd":false},{"ty":"tr","p":{"a":1,"k":[{"i":{"x":0,"y":1},"o":{"x":0.333,"y":0},"t":0,"s":[170.149,163.047],"to":[-15.593,5.815],"ti":[15.593,-5.815]},{"t":20.0000008146167,"s":[76.589,197.937]}],"ix":2},"a":{"a":0,"k":[0,0],"ix":1},"s":{"a":0,"k":[100,100],"ix":3},"r":{"a":0,"k":0,"ix":6},"o":{"a":1,"k":[{"i":{"x":[0.833],"y":[0.833]},"o":{"x":[0.167],"y":[0.167]},"t":0,"s":[0]},{"i":{"x":[0.833],"y":[0.833]},"o":{"x":[0.167],"y":[0.167]},"t":10,"s":[100]},{"t":20.0000008146167,"s":[100]}],"ix":7},"sk":{"a":0,"k":0,"ix":4},"sa":{"a":0,"k":0,"ix":5},"nm":"Transform"}],"nm":"Group 1","np":2,"cix":2,"bm":0,"ix":1,"mn":"ADBE Vector Group","hd":false},{"ty":"gr","it":[{"ind":0,"ty":"sh","ix":1,"ks":{"a":0,"k":{"i":[[-2.209,0],[0,-2.209],[2.209,0],[0,2.209]],"o":[[2.209,0],[0,2.209],[-2.209,0],[0,-2.209]],"v":[[0,-4],[4,0],[0,4],[-4,0]],"c":true},"ix":2},"nm":"Path 1","mn":"ADBE Vector Shape - Group","hd":false},{"ty":"fl","c":{"a":0,"k":[1,0.796078491211,0.796078491211,1],"ix":4},"o":{"a":0,"k":100,"ix":5},"r":1,"bm":0,"nm":"Fill 1","mn":"ADBE Vector Graphic - Fill","hd":false},{"ty":"tr","p":{"a":1,"k":[{"i":{"x":0,"y":1},"o":{"x":0.333,"y":0},"t":0,"s":[170.468,163.152],"to":[-22.047,2.113],"ti":[22.047,-2.113]},{"t":20.0000008146167,"s":[38.186,175.832]}],"ix":2},"a":{"a":0,"k":[0,0],"ix":1},"s":{"a":0,"k":[100,100],"ix":3},"r":{"a":0,"k":0,"ix":6},"o":{"a":1,"k":[{"i":{"x":[0.833],"y":[0.833]},"o":{"x":[0.167],"y":[0.167]},"t":0,"s":[0]},{"i":{"x":[0.833],"y":[0.833]},"o":{"x":[0.167],"y":[0.167]},"t":10,"s":[100]},{"t":20.0000008146167,"s":[100]}],"ix":7},"sk":{"a":0,"k":0,"ix":4},"sa":{"a":0,"k":0,"ix":5},"nm":"Transform"}],"nm":"Group 2","np":2,"cix":2,"bm":0,"ix":2,"mn":"ADBE Vector Group","hd":false},{"ty":"gr","it":[{"ind":0,"ty":"sh","ix":1,"ks":{"a":0,"k":{"i":[[-2.209,0],[0,-2.209],[2.209,0],[0,2.209]],"o":[[2.209,0],[0,2.209],[-2.209,0],[0,-2.209]],"v":[[0,-4],[4,0],[0,4],[-4,0]],"c":true},"ix":2},"nm":"Path 1","mn":"ADBE Vector Shape - Group","hd":false},{"ty":"fl","c":{"a":0,"k":[1,0.796078491211,0.796078491211,1],"ix":4},"o":{"a":0,"k":100,"ix":5},"r":1,"bm":0,"nm":"Fill 1","mn":"ADBE Vector Graphic - Fill","hd":false},{"ty":"tr","p":{"a":1,"k":[{"i":{"x":0,"y":1},"o":{"x":0.333,"y":0},"t":0,"s":[170.344,162.63],"to":[-9.724,-3.772],"ti":[9.724,3.772]},{"t":20.0000008146167,"s":[112,140]}],"ix":2},"a":{"a":0,"k":[0,0],"ix":1},"s":{"a":0,"k":[100,100],"ix":3},"r":{"a":0,"k":0,"ix":6},"o":{"a":1,"k":[{"i":{"x":[0.833],"y":[0.833]},"o":{"x":[0.167],"y":[0.167]},"t":0,"s":[0]},{"i":{"x":[0.833],"y":[0.833]},"o":{"x":[0.167],"y":[0.167]},"t":10,"s":[100]},{"t":20.0000008146167,"s":[100]}],"ix":7},"sk":{"a":0,"k":0,"ix":4},"sa":{"a":0,"k":0,"ix":5},"nm":"Transform"}],"nm":"Group 3","np":2,"cix":2,"bm":0,"ix":3,"mn":"ADBE Vector Group","hd":false},{"ty":"gr","it":[{"ind":0,"ty":"sh","ix":1,"ks":{"a":0,"k":{"i":[[-2.209,0],[0,-2.209],[2.209,0],[0,2.209]],"o":[[2.209,0],[0,2.209],[-2.209,0],[0,-2.209]],"v":[[0,-4],[4,0],[0,4],[-4,0]],"c":true},"ix":2},"nm":"Path 1","mn":"ADBE Vector Shape - Group","hd":false},{"ty":"fl","c":{"a":0,"k":[1,0.796078491211,0.796078491211,1],"ix":4},"o":{"a":0,"k":100,"ix":5},"r":1,"bm":0,"nm":"Fill 1","mn":"ADBE Vector Graphic - Fill","hd":false},{"ty":"tr","p":{"a":1,"k":[{"i":{"x":0,"y":1},"o":{"x":0.333,"y":0},"t":0,"s":[169.356,162.559],"to":[12.274,-4.26],"ti":[-12.274,4.26]},{"t":20.0000008146167,"s":[243,137]}],"ix":2},"a":{"a":0,"k":[0,0],"ix":1},"s":{"a":0,"k":[100,100],"ix":3},"r":{"a":0,"k":0,"ix":6},"o":{"a":1,"k":[{"i":{"x":[0.833],"y":[0.833]},"o":{"x":[0.167],"y":[0.167]},"t":0,"s":[0]},{"i":{"x":[0.833],"y":[0.833]},"o":{"x":[0.167],"y":[0.167]},"t":10,"s":[100]},{"t":20.0000008146167,"s":[100]}],"ix":7},"sk":{"a":0,"k":0,"ix":4},"sa":{"a":0,"k":0,"ix":5},"nm":"Transform"}],"nm":"Group 4","np":2,"cix":2,"bm":0,"ix":4,"mn":"ADBE Vector Group","hd":false},{"ty":"gr","it":[{"ind":0,"ty":"sh","ix":1,"ks":{"a":0,"k":{"i":[[-2.209,0],[0,-2.209],[2.209,0],[0,2.209]],"o":[[2.209,0],[0,2.209],[-2.209,0],[0,-2.209]],"v":[[0,-4],[4,0],[0,4],[-4,0]],"c":true},"ix":2},"nm":"Path 1","mn":"ADBE Vector Shape - Group","hd":false},{"ty":"fl","c":{"a":0,"k":[1,0.933333393172,0.698039215686,1],"ix":4},"o":{"a":0,"k":100,"ix":5},"r":1,"bm":0,"nm":"Fill 1","mn":"ADBE Vector Graphic - Fill","hd":false},{"ty":"tr","p":{"a":1,"k":[{"i":{"x":0,"y":1},"o":{"x":0.333,"y":0},"t":0,"s":[170.132,161.337],"to":[-15.355,22.777],"ti":[15.355,-22.777]},{"t":20.0000008146167,"s":[78,298]}],"ix":2},"a":{"a":0,"k":[0,0],"ix":1},"s":{"a":0,"k":[100,100],"ix":3},"r":{"a":0,"k":0,"ix":6},"o":{"a":1,"k":[{"i":{"x":[0.833],"y":[0.833]},"o":{"x":[0.167],"y":[0.167]},"t":0,"s":[0]},{"i":{"x":[0.833],"y":[0.833]},"o":{"x":[0.167],"y":[0.167]},"t":10,"s":[100]},{"t":20.0000008146167,"s":[100]}],"ix":7},"sk":{"a":0,"k":0,"ix":4},"sa":{"a":0,"k":0,"ix":5},"nm":"Transform"}],"nm":"Group 5","np":2,"cix":2,"bm":0,"ix":5,"mn":"ADBE Vector Group","hd":false},{"ty":"gr","it":[{"ind":0,"ty":"sh","ix":1,"ks":{"a":0,"k":{"i":[[-2.209,0],[0,-2.209],[2.209,0],[0,2.209]],"o":[[2.209,0],[0,2.209],[-2.209,0],[0,-2.209]],"v":[[0,-4],[4,0],[0,4],[-4,0]],"c":true},"ix":2},"nm":"Path 1","mn":"ADBE Vector Shape - Group","hd":false},{"ty":"fl","c":{"a":0,"k":[1,0.933333393172,0.698039215686,1],"ix":4},"o":{"a":0,"k":100,"ix":5},"r":1,"bm":0,"nm":"Fill 1","mn":"ADBE Vector Graphic - Fill","hd":false},{"ty":"tr","p":{"a":1,"k":[{"i":{"x":0,"y":1},"o":{"x":0.333,"y":0},"t":0,"s":[170.136,162.201],"to":[8.144,4.633],"ti":[-8.144,-4.633]},{"t":20.0000008146167,"s":[219,190]}],"ix":2},"a":{"a":0,"k":[0,0],"ix":1},"s":{"a":0,"k":[100,100],"ix":3},"r":{"a":0,"k":0,"ix":6},"o":{"a":1,"k":[{"i":{"x":[0.833],"y":[0.833]},"o":{"x":[0.167],"y":[0.167]},"t":0,"s":[0]},{"i":{"x":[0.833],"y":[0.833]},"o":{"x":[0.167],"y":[0.167]},"t":10,"s":[100]},{"t":20.0000008146167,"s":[100]}],"ix":7},"sk":{"a":0,"k":0,"ix":4},"sa":{"a":0,"k":0,"ix":5},"nm":"Transform"}],"nm":"Group 6","np":2,"cix":2,"bm":0,"ix":6,"mn":"ADBE Vector Group","hd":false},{"ty":"gr","it":[{"ind":0,"ty":"sh","ix":1,"ks":{"a":0,"k":{"i":[[-2.209,0],[0,-2.209],[2.209,0],[0,2.209]],"o":[[2.209,0],[0,2.209],[-2.209,0],[0,-2.209]],"v":[[0,-4],[4,0],[0,4],[-4,0]],"c":true},"ix":2},"nm":"Path 1","mn":"ADBE Vector Shape - Group","hd":false},{"ty":"fl","c":{"a":0,"k":[1,0.933333393172,0.698039215686,1],"ix":4},"o":{"a":0,"k":100,"ix":5},"r":1,"bm":0,"nm":"Fill 1","mn":"ADBE Vector Graphic - Fill","hd":false},{"ty":"tr","p":{"a":1,"k":[{"i":{"x":0,"y":1},"o":{"x":0.333,"y":0},"t":0,"s":[169.719,161.129],"to":[-6.12,8.145],"ti":[6.12,-8.145]},{"t":20.0000008146167,"s":[133,210]}],"ix":2},"a":{"a":0,"k":[0,0],"ix":1},"s":{"a":0,"k":[100,100],"ix":3},"r":{"a":0,"k":0,"ix":6},"o":{"a":1,"k":[{"i":{"x":[0.833],"y":[0.833]},"o":{"x":[0.167],"y":[0.167]},"t":0,"s":[0]},{"i":{"x":[0.833],"y":[0.833]},"o":{"x":[0.167],"y":[0.167]},"t":10,"s":[100]},{"t":20.0000008146167,"s":[100]}],"ix":7},"sk":{"a":0,"k":0,"ix":4},"sa":{"a":0,"k":0,"ix":5},"nm":"Transform"}],"nm":"Group 7","np":2,"cix":2,"bm":0,"ix":7,"mn":"ADBE Vector Group","hd":false},{"ty":"gr","it":[{"ind":0,"ty":"sh","ix":1,"ks":{"a":0,"k":{"i":[[-2.209,0],[0,-2.209],[2.209,0],[0,2.209]],"o":[[2.209,0],[0,2.209],[-2.209,0],[0,-2.209]],"v":[[0,-4],[4,0],[0,4],[-4,0]],"c":true},"ix":2},"nm":"Path 1","mn":"ADBE Vector Shape - Group","hd":false},{"ty":"fl","c":{"a":0,"k":[1,0.933333393172,0.698039215686,1],"ix":4},"o":{"a":0,"k":100,"ix":5},"r":1,"bm":0,"nm":"Fill 1","mn":"ADBE Vector Graphic - Fill","hd":false},{"ty":"tr","p":{"a":1,"k":[{"i":{"x":0,"y":1},"o":{"x":0.333,"y":0},"t":0,"s":[170.335,162.527],"to":[-12.223,-19.254],"ti":[12.223,19.254]},{"t":20.0000008146167,"s":[97,47]}],"ix":2},"a":{"a":0,"k":[0,0],"ix":1},"s":{"a":0,"k":[100,100],"ix":3},"r":{"a":0,"k":0,"ix":6},"o":{"a":1,"k":[{"i":{"x":[0.833],"y":[0.833]},"o":{"x":[0.167],"y":[0.167]},"t":0,"s":[0]},{"i":{"x":[0.833],"y":[0.833]},"o":{"x":[0.167],"y":[0.167]},"t":10,"s":[100]},{"t":20.0000008146167,"s":[100]}],"ix":7},"sk":{"a":0,"k":0,"ix":4},"sa":{"a":0,"k":0,"ix":5},"nm":"Transform"}],"nm":"Group 8","np":2,"cix":2,"bm":0,"ix":8,"mn":"ADBE Vector Group","hd":false},{"ty":"gr","it":[{"ind":0,"ty":"sh","ix":1,"ks":{"a":0,"k":{"i":[[-2.209,0],[0,-2.209],[2.209,0],[0,2.209]],"o":[[2.209,0],[0,2.209],[-2.209,0],[0,-2.209]],"v":[[0,-4],[4,0],[0,4],[-4,0]],"c":true},"ix":2},"nm":"Path 1","mn":"ADBE Vector Shape - Group","hd":false},{"ty":"fl","c":{"a":0,"k":[1,0.933333393172,0.698039215686,1],"ix":4},"o":{"a":0,"k":100,"ix":5},"r":1,"bm":0,"nm":"Fill 1","mn":"ADBE Vector Graphic - Fill","hd":false},{"ty":"tr","p":{"a":1,"k":[{"i":{"x":0,"y":1},"o":{"x":0.333,"y":0},"t":0,"s":[168.996,160.779],"to":[-1.833,-10.13],"ti":[1.833,10.13]},{"t":20.0000008146167,"s":[158,100]}],"ix":2},"a":{"a":0,"k":[0,0],"ix":1},"s":{"a":0,"k":[100,100],"ix":3},"r":{"a":0,"k":0,"ix":6},"o":{"a":1,"k":[{"i":{"x":[0.833],"y":[0.833]},"o":{"x":[0.167],"y":[0.167]},"t":0,"s":[0]},{"i":{"x":[0.833],"y":[0.833]},"o":{"x":[0.167],"y":[0.167]},"t":10,"s":[100]},{"t":20.0000008146167,"s":[100]}],"ix":7},"sk":{"a":0,"k":0,"ix":4},"sa":{"a":0,"k":0,"ix":5},"nm":"Transform"}],"nm":"Group 9","np":2,"cix":2,"bm":0,"ix":9,"mn":"ADBE Vector Group","hd":false},{"ty":"gr","it":[{"ind":0,"ty":"sh","ix":1,"ks":{"a":0,"k":{"i":[[-2.209,0],[0,-2.209],[2.209,0],[0,2.209]],"o":[[2.209,0],[0,2.209],[-2.209,0],[0,-2.209]],"v":[[0,-4],[4,0],[0,4],[-4,0]],"c":true},"ix":2},"nm":"Path 1","mn":"ADBE Vector Shape - Group","hd":false},{"ty":"fl","c":{"a":0,"k":[1,0.933333393172,0.698039215686,1],"ix":4},"o":{"a":0,"k":100,"ix":5},"r":1,"bm":0,"nm":"Fill 1","mn":"ADBE Vector Graphic - Fill","hd":false},{"ty":"tr","p":{"a":1,"k":[{"i":{"x":0,"y":1},"o":{"x":0.333,"y":0},"t":0,"s":[170.442,164.432],"to":[20.426,14.595],"ti":[-20.426,-14.595]},{"t":20.0000008146167,"s":[293,252]}],"ix":2},"a":{"a":0,"k":[0,0],"ix":1},"s":{"a":0,"k":[100,100],"ix":3},"r":{"a":0,"k":0,"ix":6},"o":{"a":1,"k":[{"i":{"x":[0.833],"y":[0.833]},"o":{"x":[0.167],"y":[0.167]},"t":0,"s":[0]},{"i":{"x":[0.833],"y":[0.833]},"o":{"x":[0.167],"y":[0.167]},"t":10,"s":[100]},{"t":20.0000008146167,"s":[100]}],"ix":7},"sk":{"a":0,"k":0,"ix":4},"sa":{"a":0,"k":0,"ix":5},"nm":"Transform"}],"nm":"Group 10","np":2,"cix":2,"bm":0,"ix":10,"mn":"ADBE Vector Group","hd":false},{"ty":"gr","it":[{"ind":0,"ty":"sh","ix":1,"ks":{"a":0,"k":{"i":[[-2.209,0],[0,-2.209],[2.209,0],[0,2.209]],"o":[[2.209,0],[0,2.209],[-2.209,0],[0,-2.209]],"v":[[0,-4],[4,0],[0,4],[-4,0]],"c":true},"ix":2},"nm":"Path 1","mn":"ADBE Vector Shape - Group","hd":false},{"ty":"fl","c":{"a":0,"k":[1,0.933333393172,0.698039215686,1],"ix":4},"o":{"a":0,"k":100,"ix":5},"r":1,"bm":0,"nm":"Fill 1","mn":"ADBE Vector Graphic - Fill","hd":false},{"ty":"tr","p":{"a":1,"k":[{"i":{"x":0,"y":1},"o":{"x":0.333,"y":0},"t":0,"s":[170.622,161.742],"to":[13.396,5.376],"ti":[-13.396,-5.376]},{"t":20.0000008146167,"s":[251,194]}],"ix":2},"a":{"a":0,"k":[0,0],"ix":1},"s":{"a":0,"k":[100,100],"ix":3},"r":{"a":0,"k":0,"ix":6},"o":{"a":1,"k":[{"i":{"x":[0.833],"y":[0.833]},"o":{"x":[0.167],"y":[0.167]},"t":0,"s":[0]},{"i":{"x":[0.833],"y":[0.833]},"o":{"x":[0.167],"y":[0.167]},"t":10,"s":[100]},{"t":20.0000008146167,"s":[100]}],"ix":7},"sk":{"a":0,"k":0,"ix":4},"sa":{"a":0,"k":0,"ix":5},"nm":"Transform"}],"nm":"Group 11","np":2,"cix":2,"bm":0,"ix":11,"mn":"ADBE Vector Group","hd":false},{"ty":"gr","it":[{"ind":0,"ty":"sh","ix":1,"ks":{"a":0,"k":{"i":[[-2.209,0],[0,-2.209],[2.209,0],[0,2.209]],"o":[[2.209,0],[0,2.209],[-2.209,0],[0,-2.209]],"v":[[0,-4],[4,0],[0,4],[-4,0]],"c":true},"ix":2},"nm":"Path 1","mn":"ADBE Vector Shape - Group","hd":false},{"ty":"fl","c":{"a":0,"k":[0.796078491211,0.901960844152,1,1],"ix":4},"o":{"a":0,"k":100,"ix":5},"r":1,"bm":0,"nm":"Fill 1","mn":"ADBE Vector Graphic - Fill","hd":false},{"ty":"tr","p":{"a":1,"k":[{"i":{"x":0,"y":1},"o":{"x":0.333,"y":0},"t":0,"s":[169.157,161.652],"to":[-9.86,-8.275],"ti":[9.86,8.275]},{"t":20.0000008146167,"s":[110,112]}],"ix":2},"a":{"a":0,"k":[0,0],"ix":1},"s":{"a":0,"k":[100,100],"ix":3},"r":{"a":0,"k":0,"ix":6},"o":{"a":1,"k":[{"i":{"x":[0.833],"y":[0.833]},"o":{"x":[0.167],"y":[0.167]},"t":0,"s":[0]},{"i":{"x":[0.833],"y":[0.833]},"o":{"x":[0.167],"y":[0.167]},"t":10,"s":[100]},{"t":20.0000008146167,"s":[100]}],"ix":7},"sk":{"a":0,"k":0,"ix":4},"sa":{"a":0,"k":0,"ix":5},"nm":"Transform"}],"nm":"Group 12","np":2,"cix":2,"bm":0,"ix":12,"mn":"ADBE Vector Group","hd":false},{"ty":"gr","it":[{"ind":0,"ty":"sh","ix":1,"ks":{"a":0,"k":{"i":[[-2.209,0],[0,-2.209],[2.209,0],[0,2.209]],"o":[[2.209,0],[0,2.209],[-2.209,0],[0,-2.209]],"v":[[0,-4],[4,0],[0,4],[-4,0]],"c":true},"ix":2},"nm":"Path 1","mn":"ADBE Vector Shape - Group","hd":false},{"ty":"fl","c":{"a":0,"k":[0.796078491211,0.901960844152,1,1],"ix":4},"o":{"a":0,"k":100,"ix":5},"r":1,"bm":0,"nm":"Fill 1","mn":"ADBE Vector Graphic - Fill","hd":false},{"ty":"tr","p":{"a":1,"k":[{"i":{"x":0,"y":1},"o":{"x":0.333,"y":0},"t":0,"s":[169.405,162.684],"to":[-12.901,-9.781],"ti":[12.901,9.781]},{"t":20.0000008146167,"s":[92,104]}],"ix":2},"a":{"a":0,"k":[0,0],"ix":1},"s":{"a":0,"k":[100,100],"ix":3},"r":{"a":0,"k":0,"ix":6},"o":{"a":1,"k":[{"i":{"x":[0.833],"y":[0.833]},"o":{"x":[0.167],"y":[0.167]},"t":0,"s":[0]},{"i":{"x":[0.833],"y":[0.833]},"o":{"x":[0.167],"y":[0.167]},"t":10,"s":[100]},{"t":20.0000008146167,"s":[100]}],"ix":7},"sk":{"a":0,"k":0,"ix":4},"sa":{"a":0,"k":0,"ix":5},"nm":"Transform"}],"nm":"Group 13","np":2,"cix":2,"bm":0,"ix":13,"mn":"ADBE Vector Group","hd":false},{"ty":"gr","it":[{"ind":0,"ty":"sh","ix":1,"ks":{"a":0,"k":{"i":[[-2.209,0],[0,-2.209],[2.209,0],[0,2.209]],"o":[[2.209,0],[0,2.209],[-2.209,0],[0,-2.209]],"v":[[0,-4],[4,0],[0,4],[-4,0]],"c":true},"ix":2},"nm":"Path 1","mn":"ADBE Vector Shape - Group","hd":false},{"ty":"fl","c":{"a":0,"k":[0.796078491211,0.901960844152,1,1],"ix":4},"o":{"a":0,"k":100,"ix":5},"r":1,"bm":0,"nm":"Fill 1","mn":"ADBE Vector Graphic - Fill","hd":false},{"ty":"tr","p":{"a":1,"k":[{"i":{"x":0,"y":1},"o":{"x":0.333,"y":0},"t":0,"s":[170.054,162.442],"to":[3.824,-6.574],"ti":[-3.824,6.574]},{"t":20.0000008146167,"s":[193,123]}],"ix":2},"a":{"a":0,"k":[0,0],"ix":1},"s":{"a":0,"k":[100,100],"ix":3},"r":{"a":0,"k":0,"ix":6},"o":{"a":1,"k":[{"i":{"x":[0.833],"y":[0.833]},"o":{"x":[0.167],"y":[0.167]},"t":0,"s":[0]},{"i":{"x":[0.833],"y":[0.833]},"o":{"x":[0.167],"y":[0.167]},"t":10,"s":[100]},{"t":20.0000008146167,"s":[100]}],"ix":7},"sk":{"a":0,"k":0,"ix":4},"sa":{"a":0,"k":0,"ix":5},"nm":"Transform"}],"nm":"Group 15","np":2,"cix":2,"bm":0,"ix":14,"mn":"ADBE Vector Group","hd":false},{"ty":"gr","it":[{"ind":0,"ty":"sh","ix":1,"ks":{"a":0,"k":{"i":[[-2.209,0],[0,-2.209],[2.209,0],[0,2.209]],"o":[[2.209,0],[0,2.209],[-2.209,0],[0,-2.209]],"v":[[0,-4],[4,0],[0,4],[-4,0]],"c":true},"ix":2},"nm":"Path 1","mn":"ADBE Vector Shape - Group","hd":false},{"ty":"fl","c":{"a":0,"k":[0.796078491211,0.901960844152,1,1],"ix":4},"o":{"a":0,"k":100,"ix":5},"r":1,"bm":0,"nm":"Fill 1","mn":"ADBE Vector Graphic - Fill","hd":false},{"ty":"tr","p":{"a":1,"k":[{"i":{"x":0,"y":1},"o":{"x":0.333,"y":0},"t":0,"s":[169.759,162.843],"to":[-2.627,11.193],"ti":[2.627,-11.193]},{"t":20.0000008146167,"s":[154,230]}],"ix":2},"a":{"a":0,"k":[0,0],"ix":1},"s":{"a":0,"k":[100,100],"ix":3},"r":{"a":0,"k":0,"ix":6},"o":{"a":1,"k":[{"i":{"x":[0.833],"y":[0.833]},"o":{"x":[0.167],"y":[0.167]},"t":0,"s":[0]},{"i":{"x":[0.833],"y":[0.833]},"o":{"x":[0.167],"y":[0.167]},"t":10,"s":[100]},{"t":20.0000008146167,"s":[100]}],"ix":7},"sk":{"a":0,"k":0,"ix":4},"sa":{"a":0,"k":0,"ix":5},"nm":"Transform"}],"nm":"Group 16","np":2,"cix":2,"bm":0,"ix":15,"mn":"ADBE Vector Group","hd":false},{"ty":"gr","it":[{"ind":0,"ty":"sh","ix":1,"ks":{"a":0,"k":{"i":[[-2.209,0],[0,-2.209],[2.209,0],[0,2.209]],"o":[[2.209,0],[0,2.209],[-2.209,0],[0,-2.209]],"v":[[0,-4],[4,0],[0,4],[-4,0]],"c":true},"ix":2},"nm":"Path 1","mn":"ADBE Vector Shape - Group","hd":false},{"ty":"fl","c":{"a":0,"k":[0.796078491211,0.901960844152,1,1],"ix":4},"o":{"a":0,"k":100,"ix":5},"r":1,"bm":0,"nm":"Fill 1","mn":"ADBE Vector Graphic - Fill","hd":false},{"ty":"tr","p":{"a":1,"k":[{"i":{"x":0,"y":1},"o":{"x":0.333,"y":0},"t":0,"s":[170.283,163.36],"to":[16.453,22.44],"ti":[-16.453,-22.44]},{"t":20.0000008146167,"s":[269,298]}],"ix":2},"a":{"a":0,"k":[0,0],"ix":1},"s":{"a":0,"k":[100,100],"ix":3},"r":{"a":0,"k":0,"ix":6},"o":{"a":1,"k":[{"i":{"x":[0.833],"y":[0.833]},"o":{"x":[0.167],"y":[0.167]},"t":0,"s":[0]},{"i":{"x":[0.833],"y":[0.833]},"o":{"x":[0.167],"y":[0.167]},"t":10,"s":[100]},{"t":20.0000008146167,"s":[100]}],"ix":7},"sk":{"a":0,"k":0,"ix":4},"sa":{"a":0,"k":0,"ix":5},"nm":"Transform"}],"nm":"Group 17","np":2,"cix":2,"bm":0,"ix":16,"mn":"ADBE Vector Group","hd":false},{"ty":"gr","it":[{"ind":0,"ty":"sh","ix":1,"ks":{"a":0,"k":{"i":[[-2.209,0],[0,-2.209],[2.209,0],[0,2.209]],"o":[[2.209,0],[0,2.209],[-2.209,0],[0,-2.209]],"v":[[0,-4],[4,0],[0,4],[-4,0]],"c":true},"ix":2},"nm":"Path 1","mn":"ADBE Vector Shape - Group","hd":false},{"ty":"fl","c":{"a":0,"k":[0.796078491211,0.901960844152,1,1],"ix":4},"o":{"a":0,"k":100,"ix":5},"r":1,"bm":0,"nm":"Fill 1","mn":"ADBE Vector Graphic - Fill","hd":false},{"ty":"tr","p":{"a":1,"k":[{"i":{"x":0,"y":1},"o":{"x":0.333,"y":0},"t":0,"s":[169.062,161.955],"to":[1.156,28.674],"ti":[-1.156,-28.674]},{"t":20.0000008146167,"s":[176,334]}],"ix":2},"a":{"a":0,"k":[0,0],"ix":1},"s":{"a":0,"k":[100,100],"ix":3},"r":{"a":0,"k":0,"ix":6},"o":{"a":1,"k":[{"i":{"x":[0.833],"y":[0.833]},"o":{"x":[0.167],"y":[0.167]},"t":0,"s":[0]},{"i":{"x":[0.833],"y":[0.833]},"o":{"x":[0.167],"y":[0.167]},"t":10,"s":[100]},{"t":20.0000008146167,"s":[100]}],"ix":7},"sk":{"a":0,"k":0,"ix":4},"sa":{"a":0,"k":0,"ix":5},"nm":"Transform"}],"nm":"Group 18","np":2,"cix":2,"bm":0,"ix":17,"mn":"ADBE Vector Group","hd":false},{"ty":"gr","it":[{"ind":0,"ty":"sh","ix":1,"ks":{"a":0,"k":{"i":[[-2.209,0],[0,-2.209],[2.209,0],[0,2.209]],"o":[[2.209,0],[0,2.209],[-2.209,0],[0,-2.209]],"v":[[0,-4],[4,0],[0,4],[-4,0]],"c":true},"ix":2},"nm":"Path 1","mn":"ADBE Vector Shape - Group","hd":false},{"ty":"fl","c":{"a":0,"k":[0.796078491211,0.901960844152,1,1],"ix":4},"o":{"a":0,"k":100,"ix":5},"r":1,"bm":0,"nm":"Fill 1","mn":"ADBE Vector Graphic - Fill","hd":false},{"ty":"tr","p":{"a":1,"k":[{"i":{"x":0,"y":1},"o":{"x":0.333,"y":0},"t":0,"s":[169.515,162.366],"to":[4.581,7.272],"ti":[-4.581,-7.272]},{"t":20.0000008146167,"s":[197,206]}],"ix":2},"a":{"a":0,"k":[0,0],"ix":1},"s":{"a":0,"k":[100,100],"ix":3},"r":{"a":0,"k":0,"ix":6},"o":{"a":1,"k":[{"i":{"x":[0.833],"y":[0.833]},"o":{"x":[0.167],"y":[0.167]},"t":0,"s":[0]},{"i":{"x":[0.833],"y":[0.833]},"o":{"x":[0.167],"y":[0.167]},"t":10,"s":[100]},{"t":20.0000008146167,"s":[100]}],"ix":7},"sk":{"a":0,"k":0,"ix":4},"sa":{"a":0,"k":0,"ix":5},"nm":"Transform"}],"nm":"Group 19","np":2,"cix":2,"bm":0,"ix":18,"mn":"ADBE Vector Group","hd":false},{"ty":"gr","it":[{"ind":0,"ty":"sh","ix":1,"ks":{"a":0,"k":{"i":[[-2.209,0],[0,-2.209],[2.209,0],[0,2.209]],"o":[[2.209,0],[0,2.209],[-2.209,0],[0,-2.209]],"v":[[0,-4],[4,0],[0,4],[-4,0]],"c":true},"ix":2},"nm":"Path 1","mn":"ADBE Vector Shape - Group","hd":false},{"ty":"fl","c":{"a":0,"k":[0.796078491211,0.901960844152,1,1],"ix":4},"o":{"a":0,"k":100,"ix":5},"r":1,"bm":0,"nm":"Fill 1","mn":"ADBE Vector Graphic - Fill","hd":false},{"ty":"tr","p":{"a":1,"k":[{"i":{"x":0,"y":1},"o":{"x":0.333,"y":0},"t":0,"s":[168.946,162.228],"to":[6.009,11.295],"ti":[-6.009,-11.295]},{"t":20.0000008146167,"s":[205,230]}],"ix":2},"a":{"a":0,"k":[0,0],"ix":1},"s":{"a":0,"k":[100,100],"ix":3},"r":{"a":0,"k":0,"ix":6},"o":{"a":1,"k":[{"i":{"x":[0.833],"y":[0.833]},"o":{"x":[0.167],"y":[0.167]},"t":0,"s":[0]},{"i":{"x":[0.833],"y":[0.833]},"o":{"x":[0.167],"y":[0.167]},"t":10,"s":[100]},{"t":20.0000008146167,"s":[100]}],"ix":7},"sk":{"a":0,"k":0,"ix":4},"sa":{"a":0,"k":0,"ix":5},"nm":"Transform"}],"nm":"Group 20","np":2,"cix":2,"bm":0,"ix":19,"mn":"ADBE Vector Group","hd":false},{"ty":"gr","it":[{"ind":0,"ty":"sh","ix":1,"ks":{"a":0,"k":{"i":[[-2.209,0],[0,-2.209],[2.209,0],[0,2.209]],"o":[[2.209,0],[0,2.209],[-2.209,0],[0,-2.209]],"v":[[0,-4],[4,0],[0,4],[-4,0]],"c":true},"ix":2},"nm":"Path 1","mn":"ADBE Vector Shape - Group","hd":false},{"ty":"fl","c":{"a":0,"k":[0.796078491211,0.901960844152,1,1],"ix":4},"o":{"a":0,"k":100,"ix":5},"r":1,"bm":0,"nm":"Fill 1","mn":"ADBE Vector Graphic - Fill","hd":false},{"ty":"tr","p":{"a":1,"k":[{"i":{"x":0,"y":1},"o":{"x":0.333,"y":0},"t":0,"s":[168.899,161.825],"to":[6.517,-10.971],"ti":[-6.517,10.971]},{"t":20.0000008146167,"s":[208,96]}],"ix":2},"a":{"a":0,"k":[0,0],"ix":1},"s":{"a":0,"k":[100,100],"ix":3},"r":{"a":0,"k":0,"ix":6},"o":{"a":1,"k":[{"i":{"x":[0.833],"y":[0.833]},"o":{"x":[0.167],"y":[0.167]},"t":0,"s":[0]},{"i":{"x":[0.833],"y":[0.833]},"o":{"x":[0.167],"y":[0.167]},"t":10,"s":[100]},{"t":20.0000008146167,"s":[100]}],"ix":7},"sk":{"a":0,"k":0,"ix":4},"sa":{"a":0,"k":0,"ix":5},"nm":"Transform"}],"nm":"Group 21","np":2,"cix":2,"bm":0,"ix":20,"mn":"ADBE Vector Group","hd":false},{"ty":"gr","it":[{"ind":0,"ty":"sh","ix":1,"ks":{"a":0,"k":{"i":[[-2.209,0],[0,-2.209],[2.209,0],[0,2.209]],"o":[[2.209,0],[0,2.209],[-2.209,0],[0,-2.209]],"v":[[0,-4],[4,0],[0,4],[-4,0]],"c":true},"ix":2},"nm":"Path 1","mn":"ADBE Vector Shape - Group","hd":false},{"ty":"fl","c":{"a":0,"k":[1,0.796078491211,0.796078491211,1],"ix":4},"o":{"a":0,"k":100,"ix":5},"r":1,"bm":0,"nm":"Fill 1","mn":"ADBE Vector Graphic - Fill","hd":false},{"ty":"tr","p":{"a":1,"k":[{"i":{"x":0,"y":1},"o":{"x":0.333,"y":0},"t":0,"s":[169.276,162.997],"to":[13.954,-20.666],"ti":[-13.954,20.666]},{"t":20.0000008146167,"s":[253,39]}],"ix":2},"a":{"a":0,"k":[0,0],"ix":1},"s":{"a":0,"k":[100,100],"ix":3},"r":{"a":0,"k":0,"ix":6},"o":{"a":1,"k":[{"i":{"x":[0.833],"y":[0.833]},"o":{"x":[0.167],"y":[0.167]},"t":0,"s":[0]},{"i":{"x":[0.833],"y":[0.833]},"o":{"x":[0.167],"y":[0.167]},"t":10,"s":[100]},{"t":20.0000008146167,"s":[100]}],"ix":7},"sk":{"a":0,"k":0,"ix":4},"sa":{"a":0,"k":0,"ix":5},"nm":"Transform"}],"nm":"Group 22","np":2,"cix":2,"bm":0,"ix":21,"mn":"ADBE Vector Group","hd":false},{"ty":"gr","it":[{"ind":0,"ty":"sh","ix":1,"ks":{"a":0,"k":{"i":[[-2.209,0],[0,-2.209],[2.209,0],[0,2.209]],"o":[[2.209,0],[0,2.209],[-2.209,0],[0,-2.209]],"v":[[0,-4],[4,0],[0,4],[-4,0]],"c":true},"ix":2},"nm":"Path 1","mn":"ADBE Vector Shape - Group","hd":false},{"ty":"fl","c":{"a":0,"k":[1,0.796078491211,0.796078491211,1],"ix":4},"o":{"a":0,"k":100,"ix":5},"r":1,"bm":0,"nm":"Fill 1","mn":"ADBE Vector Graphic - Fill","hd":false},{"ty":"tr","p":{"a":1,"k":[{"i":{"x":0,"y":1},"o":{"x":0.333,"y":0},"t":0,"s":[171.246,162.678],"to":[-5.708,-8.446],"ti":[5.708,8.446]},{"t":20.0000008146167,"s":[137,112]}],"ix":2},"a":{"a":0,"k":[0,0],"ix":1},"s":{"a":0,"k":[100,100],"ix":3},"r":{"a":0,"k":0,"ix":6},"o":{"a":1,"k":[{"i":{"x":[0.833],"y":[0.833]},"o":{"x":[0.167],"y":[0.167]},"t":0,"s":[0]},{"i":{"x":[0.833],"y":[0.833]},"o":{"x":[0.167],"y":[0.167]},"t":10,"s":[100]},{"t":20.0000008146167,"s":[100]}],"ix":7},"sk":{"a":0,"k":0,"ix":4},"sa":{"a":0,"k":0,"ix":5},"nm":"Transform"}],"nm":"Group 23","np":2,"cix":2,"bm":0,"ix":22,"mn":"ADBE Vector Group","hd":false}],"ip":0,"op":90.0000036657751,"st":0,"bm":0}],"markers":[]}